not_my_ex/__init__.py
not_my_ex/__main__.py
not_my_ex/auth.py
not_my_ex/bluesky.py
not_my_ex/card.py
not_my_ex/client.py
not_my_ex/language.py
not_my_ex/mastodon.py
not_my_ex/media.py
not_my_ex/mime.py
not_my_ex/post.py
not_my_ex/settings.py
not_my_ex/cli/__init__.py
not_my_ex/cli/config.py
not_my_ex/cli/post.py
not_my_ex-1.2.0.dist-info/METADATA
not_my_ex-1.2.0.dist-info/WHEEL
not_my_ex-1.2.0.dist-info/entry_points.txt
not_my_ex-1.2.0.dist-info/licenses/LICENSE
not_my_ex-1.2.0.dist-info/RECORD
