Metadata-Version: 2.4
Name: not-my-ex
Version: 1.2.0
Summary: Tiny CLI to post simultaneously to Mastodon and Bluesky
Project-URL: Repository, https://codeberg.org/cuducos/not-my-ex
Project-URL: Changelog, https://codeberg.org/cuducos/not-my-ex/src/branch/main/CHANGELOG.md
Project-URL: Bug, https://codeberg.org/cuducos/not-my-ex/issues
Project-URL: Funding, https://github.com/sponsors/cuducos
Author-email: Eduardo Cuducos <4732915+cuducos@users.noreply.github.com>
License:                     GNU GENERAL PUBLIC LICENSE
License-File: LICENSE
Classifier: Intended Audience :: Developers
Classifier: License :: OSI Approved :: GNU General Public License v3 (GPLv3)
Classifier: Programming Language :: Python :: 3.10
Classifier: Programming Language :: Python :: 3.11
Classifier: Programming Language :: Python :: 3.12
Classifier: Programming Language :: Python :: 3.13
Classifier: Programming Language :: Python :: 3.14
Requires-Python: <3.15,>=3.10
Requires-Dist: aiofiles>=24.1.0
Requires-Dist: appdirs>=1.4.4
Requires-Dist: backoff>=2.2.1
Requires-Dist: beautifulsoup4>=4.12.3
Requires-Dist: cryptography>=43.0.1
Requires-Dist: eld>=1.0.6
Requires-Dist: httpx>=0.28.1
Requires-Dist: typer>=0.12.5
